svg2json/__init__.py
svg2json/svg2json.py
svg2json-0.2.0.dist-info/LICENSE
svg2json-0.2.0.dist-info/METADATA
svg2json-0.2.0.dist-info/WHEEL
svg2json-0.2.0.dist-info/entry_points.txt
svg2json-0.2.0.dist-info/top_level.txt
svg2json-0.2.0.dist-info/RECORD
