Metadata-Version: 2.1
Name: svg2json
Version: 0.2.0
Summary: Collects a set of svg vector graphics into a single json file using data URIs
Home-page: https://github.com/rstemmer/svg2json
Author: Ralf Stemmer
Author-email: ralf.stemmer@gmx.net
License: Apache Software License
Project-URL: Documentation, https://github.com/rstemmer/svg2json
Project-URL: Source, https://github.com/rstemmer/svg2json
Project-URL: Tracker, https://github.com/rstemmer/svg2json/issues
Keywords: json svg web-development
Platform: UNKNOWN
Classifier: Programming Language :: Python :: 3
Classifier: Programming Language :: Python :: 3.8
Classifier: Programming Language :: Python :: 3.9
Classifier: Programming Language :: Python :: 3.10
Classifier: Development Status :: 4 - Beta
Classifier: License :: OSI Approved :: Apache Software License
Classifier: Operating System :: POSIX :: Linux
Classifier: Environment :: Console
Classifier: Intended Audience :: End Users/Desktop
Classifier: Intended Audience :: Developers
Classifier: Intended Audience :: Science/Research
Classifier: Topic :: Internet
Classifier: Topic :: Multimedia :: Graphics :: Graphics Conversion
Classifier: Topic :: Software Development :: Build Tools
Classifier: Topic :: Utilities
Requires-Python: >=3.8
License-File: LICENSE
Requires-Dist: scour
